setup.py
yammy/__init__.py
yammy/cmdline.py
yammy/django_loaders.py
yammy/jingo_loaders.py
yammy/jinja2_loaders.py
yammy/translator.py
yammy.egg-info/PKG-INFO
yammy.egg-info/SOURCES.txt
yammy.egg-info/dependency_links.txt
yammy.egg-info/entry_points.txt
yammy.egg-info/top_level.txt