Metadata-Version: 1.0
Name: yammy
Version: 0.5.4
Summary: Yammy: A better way to create a Django/Jinja template
Home-page: https://bitbucket.org/quasinerd/yammy
Author: Vlad Glushchuk
Author-email: high.slopes@gmail.com
License: GPL
Keywords: templates html django python
Platform: UNKNOWN
